socorrolib/__init__.py
socorrolib/app/__init__.py
socorrolib/app/example_app.py
socorrolib/app/fetch_transform_save_app.py
socorrolib/app/for_application_defaults.py
socorrolib/app/generic_app.py
socorrolib/app/socorro_app.py
socorrolib/lib/__init__.py
socorrolib/lib/buildtype.py
socorrolib/lib/citexttype.py
socorrolib/lib/context_tools.py
socorrolib/lib/converters.py
socorrolib/lib/datetimeutil.py
socorrolib/lib/external_common.py
socorrolib/lib/httpclient.py
socorrolib/lib/jsontype.py
socorrolib/lib/migrations.py
socorrolib/lib/ooid.py
socorrolib/lib/prioritize.py
socorrolib/lib/sqlutils.py
socorrolib/lib/statistics.py
socorrolib/lib/task_manager.py
socorrolib/lib/threaded_task_manager.py
socorrolib/lib/threadlib.py
socorrolib/lib/transform_rules.py
socorrolib/lib/util.py
socorrolib/lib/ver_tools.py
socorrolib/unittest/__init__.py
socorrolib/unittest/skip_if.py
socorrolib/unittest/test_skip_if.py
socorrolib/unittest/testbase.py
socorrolib/unittest/app/__init__.py
socorrolib/unittest/app/test_for_application_defaults.py
socorrolib/unittest/app/test_generic_app.py
socorrolib/unittest/app/test_generic_fetch_transform_save_app.py
socorrolib/unittest/app/test_socorro_app.py
socorrolib/unittest/lib/__init__.py
socorrolib/unittest/lib/optionfile.py
socorrolib/unittest/lib/testOoid.py
socorrolib/unittest/lib/testPrioritize.py
socorrolib/unittest/lib/testVerTools.py
socorrolib/unittest/lib/test_converters.py
socorrolib/unittest/lib/test_datetimeutil.py
socorrolib/unittest/lib/test_external_common.py
socorrolib/unittest/lib/test_sqlutils.py
socorrolib/unittest/lib/test_statistics.py
socorrolib/unittest/lib/test_task_manager.py
socorrolib/unittest/lib/test_threaded_task_manager.py
socorrolib/unittest/lib/test_transform_rules.py
socorrolib-0.2.3.dist-info/top_level.txt
socorrolib-0.2.3.dist-info/METADATA
socorrolib-0.2.3.dist-info/DESCRIPTION.rst
socorrolib-0.2.3.dist-info/metadata.json
socorrolib-0.2.3.dist-info/WHEEL
socorrolib-0.2.3.dist-info/RECORD
