Metadata-Version: 2.0
Name: socorrolib
Version: 0.2.3
Summary: the common library of the socorro crash reporter
Home-page: https://github.com/mozilla/socorrolib
Author: mozilla socorro team and friends
Author-email: UNKNOWN
License: MPL-2
Platform: UNKNOWN
Classifier: Development Status :: 4 - Beta
Classifier: Environment :: Console
Classifier: License :: OSI Approved :: Mozilla Public License 2.0 (MPL 2.0)
Classifier: Programming Language :: Python
Classifier: Programming Language :: Python :: 2.7
Classifier: Intended Audience :: Developers
Requires-Dist: isodate (==0.5.4)
Requires-Dist: psycopg2 (==2.6.1)
Requires-Dist: SQLAlchemy (==0.9.8)
Requires-Dist: statsd (==2.1.2)
Requires-Dist: ujson (==1.35)
Requires-Dist: configman (==1.2.11)
Requires-Dist: configobj (==4.7.2)
Requires-Dist: contextlib2 (==0.4.0)
Requires-Dist: mccabe (==0.3.1)
Requires-Dist: flake8 (==2.5.2)
Requires-Dist: mock (==0.8.0)
Requires-Dist: nose (==1.3.0)
Requires-Dist: pep8 (==1.7.0)
Requires-Dist: pyflakes (==1.0.0)
